{
	"name": "ETL_vacunas",
	"properties": {
		"activities": [
			{
				"name": "bronze_municipios",
				"type": "ExecuteDataFlow",
				"dependsOn": [],
				"policy": {
					"retry": 0,
					"retryIntervalInSeconds": 30,
					"secureOutput": false,
					"secureInput": false
				},
				"userProperties": [],
				"typeProperties": {
					"dataflow": {
						"referenceName": "df_bronze_catalogo_departamento",
						"type": "DataFlowReference"
					},
					"compute": {
						"coreCount": 8,
						"computeType": "General"
					},
					"traceLevel": "Fine"
				}
			},
			{
				"name": "bronze_establecimientos",
				"type": "ExecuteDataFlow",
				"dependsOn": [
					{
						"activity": "bronze_municipios",
						"dependencyConditions": [
							"Succeeded"
						]
					}
				],
				"policy": {
					"retry": 0,
					"retryIntervalInSeconds": 30,
					"secureOutput": false,
					"secureInput": false
				},
				"userProperties": [],
				"typeProperties": {
					"dataflow": {
						"referenceName": "df_bronze_catalogo_establecimientos",
						"type": "DataFlowReference"
					},
					"compute": {
						"coreCount": 8,
						"computeType": "General"
					},
					"traceLevel": "Fine"
				}
			},
			{
				"name": "bronze_vacunas",
				"type": "ExecuteDataFlow",
				"dependsOn": [
					{
						"activity": "bronze_establecimientos",
						"dependencyConditions": [
							"Succeeded"
						]
					}
				],
				"policy": {
					"retry": 0,
					"retryIntervalInSeconds": 30,
					"secureOutput": false,
					"secureInput": false
				},
				"userProperties": [],
				"typeProperties": {
					"dataflow": {
						"referenceName": "df_bronze_catalogo_vacunas_pai",
						"type": "DataFlowReference"
					},
					"compute": {
						"coreCount": 8,
						"computeType": "General"
					},
					"traceLevel": "Fine"
				}
			},
			{
				"name": "bronze_vacunacion_consolidada",
				"type": "ExecuteDataFlow",
				"dependsOn": [
					{
						"activity": "bronze_vacunas",
						"dependencyConditions": [
							"Succeeded"
						]
					}
				],
				"policy": {
					"retry": 0,
					"retryIntervalInSeconds": 30,
					"secureOutput": false,
					"secureInput": false
				},
				"userProperties": [],
				"typeProperties": {
					"dataflow": {
						"referenceName": "df_bronze_vacunacion_consolidada",
						"type": "DataFlowReference"
					},
					"compute": {
						"coreCount": 8,
						"computeType": "General"
					},
					"traceLevel": "Fine"
				}
			},
			{
				"name": "Script_limpiar_gold",
				"type": "Script",
				"dependsOn": [
					{
						"activity": "bronze_vacunacion_consolidada",
						"dependencyConditions": [
							"Succeeded"
						]
					}
				],
				"policy": {
					"retry": 0,
					"retryIntervalInSeconds": 30,
					"secureOutput": false,
					"secureInput": false
				},
				"userProperties": [],
				"linkedServiceName": {
					"referenceName": "dw_vacunas",
					"type": "LinkedServiceReference"
				},
				"typeProperties": {
					"scripts": [
						{
							"type": "NonQuery",
							"text": "DELETE from gold.dim_establecimiento;\nDELETE from gold.dim_paciente;\nDELETE from gold.dim_vacuna;\nDELETE from gold.dim_tiempo;\nDELETE from gold.hechos_vacunacion"
						}
					],
					"scriptBlockExecutionTimeout": "02:00:00"
				}
			},
			{
				"name": "gold_dim_establecimiento",
				"type": "ExecuteDataFlow",
				"dependsOn": [
					{
						"activity": "Script_limpiar_gold",
						"dependencyConditions": [
							"Succeeded"
						]
					}
				],
				"policy": {
					"retry": 0,
					"retryIntervalInSeconds": 30,
					"secureOutput": false,
					"secureInput": false
				},
				"userProperties": [],
				"typeProperties": {
					"dataflow": {
						"referenceName": "df_gold_dim_establecimiento",
						"type": "DataFlowReference"
					},
					"compute": {
						"coreCount": 8,
						"computeType": "General"
					},
					"traceLevel": "Fine"
				}
			},
			{
				"name": "gold_dim_paciente",
				"type": "ExecuteDataFlow",
				"dependsOn": [
					{
						"activity": "gold_dim_establecimiento",
						"dependencyConditions": [
							"Succeeded"
						]
					}
				],
				"policy": {
					"retry": 0,
					"retryIntervalInSeconds": 30,
					"secureOutput": false,
					"secureInput": false
				},
				"userProperties": [],
				"typeProperties": {
					"dataflow": {
						"referenceName": "df_gold_dim_paciente",
						"type": "DataFlowReference"
					},
					"compute": {
						"coreCount": 8,
						"computeType": "General"
					},
					"traceLevel": "Fine"
				}
			},
			{
				"name": "gold_dim_vacuna",
				"type": "ExecuteDataFlow",
				"dependsOn": [
					{
						"activity": "gold_dim_paciente",
						"dependencyConditions": [
							"Succeeded"
						]
					}
				],
				"policy": {
					"retry": 0,
					"retryIntervalInSeconds": 30,
					"secureOutput": false,
					"secureInput": false
				},
				"userProperties": [],
				"typeProperties": {
					"dataflow": {
						"referenceName": "df_gold_dim_vacuna",
						"type": "DataFlowReference"
					},
					"compute": {
						"coreCount": 8,
						"computeType": "General"
					},
					"traceLevel": "Fine"
				}
			},
			{
				"name": "gold_dim_tiempo",
				"type": "ExecuteDataFlow",
				"dependsOn": [
					{
						"activity": "gold_dim_vacuna",
						"dependencyConditions": [
							"Succeeded"
						]
					}
				],
				"policy": {
					"retry": 0,
					"retryIntervalInSeconds": 30,
					"secureOutput": false,
					"secureInput": false
				},
				"userProperties": [],
				"typeProperties": {
					"dataflow": {
						"referenceName": "df_gold_dim_tiempo",
						"type": "DataFlowReference"
					},
					"compute": {
						"coreCount": 8,
						"computeType": "General"
					},
					"traceLevel": "Fine"
				}
			},
			{
				"name": "gold_hechos_vacunacion",
				"type": "ExecuteDataFlow",
				"dependsOn": [
					{
						"activity": "gold_dim_tiempo",
						"dependencyConditions": [
							"Succeeded"
						]
					}
				],
				"policy": {
					"retry": 0,
					"retryIntervalInSeconds": 30,
					"secureOutput": false,
					"secureInput": false
				},
				"userProperties": [],
				"typeProperties": {
					"dataflow": {
						"referenceName": "df_gold_hechos_vacunacion",
						"type": "DataFlowReference"
					},
					"compute": {
						"coreCount": 8,
						"computeType": "General"
					},
					"traceLevel": "Fine"
				}
			}
		],
		"annotations": []
	}
}